solvers/__init__.py
solvers/doplo/__init__.py
solvers/doplo/doplo_solver.py
solvers/futoshiki/__init__.py
solvers/futoshiki/cell.py
solvers/futoshiki/expr.py
solvers/futoshiki/futoshiki_solver.py
solvers/futoshiki/grid.py
solvers/futoshiki/less_than_op.py
solvers/killer_sudoku/__init__.py
solvers/killer_sudoku/cell.py
solvers/killer_sudoku/grid.py
solvers/killer_sudoku/killer_sudoku_solver.py
solvers/killer_sudoku/region.py
solvers/killer_sudoku/sum_region.py
solvers/neighbourhood.py
solvers/sudoku/__init__.py
solvers/sudoku/sudoku_solver.py
solvers/suguru/__init__.py
solvers/suguru/suguru_solver.py
solvers/yakuso/__init__.py
solvers/yakuso/yakuso_solver.py
solvers/zehnergitter/__init__.py
solvers/zehnergitter/zehnergitter_solver.py
ortools_puzzle_solvers-0.0.6.dist-info/WHEEL
ortools_puzzle_solvers-0.0.6.dist-info/METADATA
ortools_puzzle_solvers-0.0.6.dist-info/license_files/LICENSE
ortools_puzzle_solvers-0.0.6.dist-info/RECORD
