Metadata-Version: 2.1
Name: ortools-puzzle-solvers
Version: 0.0.6
Summary: Constraint Solvers for common puzzles using OR-Tools.
License: MIT
Author-email: Andrin Meier <andrin@pricemeier.ch>
Requires-Python: >=3.7
Requires-Dist: ortools>=9.3.10497
Project-URL: Homepage, https://github.com/andrinmeier/solvers
